llm_cerebras/__init__.py
llm_cerebras/cerebras.py
llm_cerebras-0.1.8.dist-info/licenses/LICENSE
llm_cerebras-0.1.8.dist-info/METADATA
llm_cerebras-0.1.8.dist-info/WHEEL
llm_cerebras-0.1.8.dist-info/entry_points.txt
llm_cerebras-0.1.8.dist-info/top_level.txt
llm_cerebras-0.1.8.dist-info/RECORD
