Metadata-Version: 2.4
Name: llm-cerebras
Version: 0.1.8
Summary: Plugin for LLM adding fast Cerebras inference API support
Author: Thomas (Thomasthomas) Hughes
Author-email: irthomasthomas@gmail.com
License-Expression: Apache-2.0
Project-URL: Homepage, https://github.com/irthomasthomas/llm-cerebras
Project-URL: Changelog, https://github.com/irthomasthomas/llm-cerebras/releases
Project-URL: Issues, https://github.com/irthomasthomas/llm-cerebras/issues
Requires-Python: >3.7
License-File: LICENSE
Requires-Dist: llm
Requires-Dist: httpx
Dynamic: author-email
Dynamic: license-file
